{"url": "https://www.kohls.com/catalog/lc-lauren-conrad-jewelry.jsp?CN=Brand:LC%20Lauren%20Conrad+Department:Jewelry", "text": "We're sorry,JavaScript is required to shop Kohls.com.\n\nPlease enable JavaScript in your browser; it's quick and easy! Get instructions now.", "images": ["https://media.kohlsimg.com/is/image/kohls/order-status-icon?fmt=png-alpha", "https://www.kohls.com/snb/media/1.0.54/images/pmp_imgs/swatch-blank.png", "https://www.kohls.com/snb/media/1.0.54/images/kohls_ico.ico", "https://www.kohls.com/snb/media/images/pdp/pdp-yp-icon.png", "https://www.kohls.com/snb/media/images/pmp_imgs/pmp_search_loader.gif", "https://www.kohls.com/snb/media/1.0.54/images/kds-icons/plus-circle-icon.svg", "https://media.kohlsimg.com/is/image/kohls/AppStore-qr_code2020?scl=1&fmt=png8", "https://media.kohlsimg.com/is/content/kohls/oo_tab_icon_retina"], "top_img": "https://www.kohls.com/snb/media/1.0.54/images/kohls_ico.ico", "keywords": [], "authors": [], "canonical_link": "https://www.kohls.com/catalog/lc-lauren-conrad-jewelry.jsp?CN=Brand:LC%20Lauren%20Conrad+Department:Jewelry", "title": "LC Lauren Conrad Jewelry", "meta_data": {"viewport": "width=device-width, initial-scale=1", "title": "LC Lauren Conrad Jewelry | Kohl's", "description": "Enjoy free shipping and easy returns every day at Kohl's. Find great deals on Lauren Conrad Jewelry at Kohl's today!"}, "movies": [], "publish_date": null, "source": "https://www.kohls.com", "summary": ""}